terminalmushroom/__init__.py
terminalmushroom/__main__.py
terminalmushroom/cli.py
terminalmushroom/core.py
terminalmushroom/forest.py
terminalmushroom/forest_serialization.proto
terminalmushroom/forest_serialization_pb2.py
terminalmushroom/legacy.py
terminalmushroom/structures.py
terminalmushroom/tokenizer.py
terminalmushroom/tools.py
terminalmushroom/treetable_pb2.py
terminalmushroom-3.0.1.dist-info/WHEEL
terminalmushroom-3.0.1.dist-info/METADATA
terminalmushroom-3.0.1.dist-info/RECORD
